
{
        "list": "1",
        "cmd": "ยกเลิก",
        "personal_Id": "3135596030228",
        "bank_id": "002",
        "account_number": "30000040030",
        "name_o": "",
        "last_name_o": "",
        "input_status": "6809",
        "details": "มีบางรายการในไฟล์มีข้อมูลเลขบัตรประชาชนหรือเลขที่บัญชีซ้ำกัน",

        "list_2": "2",
        "cmd_2": "ยกเลิก",
        "personal_Id_2": "3135596030228",
        "bank_id_2": "002",
        "account_number_2": "30000040030",
        "name_o_2": "",
        "last_name_o_2": "",
        "input_status_2": "6809",
        "details_2": "มีบางรายการในไฟล์มีข้อมูลเลขบัตรประชาชนหรือเลขที่บัญชีซ้ำกัน",

        "detail": "บันทึกรายการสำเร็จ",
        "detail_2": "บันทึกรายการสำเร็จ",
        "TotalTrans": "2 รายการ", 
        "TransSuccess": "0 รายการ",
        "TransFail": "2 รายการ"
}